matrixconverters/__init__.py
matrixconverters/_version.py
matrixconverters/read_csv.py
matrixconverters/read_ptv.py
matrixconverters/save_ptv.py
matrixconverters/xarray2netcdf.py
matrixconverters/tests/__init__.py
matrixconverters/tests/matrix.csv
matrixconverters/tests/matrix_bi_format.mtx
matrixconverters/tests/matrix_bk_format.mtx
matrixconverters/tests/matrix_bl_format.mtx
matrixconverters/tests/matrix_e_format.mtx
matrixconverters/tests/matrix_o_format.mtx
matrixconverters/tests/matrix_o_format_with_dashes.mtx
matrixconverters/tests/matrix_o_format_with_zeros.mtx
matrixconverters/tests/matrix_o_format_without_names.mtx
matrixconverters/tests/matrix_or_format.mtx
matrixconverters/tests/matrix_s_format.mtx
matrixconverters/tests/matrix_v_format.mtx
matrixconverters/tests/test_read_csv.py
matrixconverters/tests/test_read_visum.py
matrixconverters/tests/test_save_psv.py
matrixconverters/tests/test_xarray2netcdf.py
matrixconverters/tests/zones.csv
matrixconverters-1.3.3.dist-info/METADATA
matrixconverters-1.3.3.dist-info/WHEEL
matrixconverters-1.3.3.dist-info/top_level.txt
matrixconverters-1.3.3.dist-info/RECORD
